modelZoo/__init__.py
modelZoo/mbnetv2.py
modelZoo/shufflenet.py
moduleZoo/__init__.py
moduleZoo/utils.py
moduleZoo/attention/__init__.py
moduleZoo/attention/conv_multi_head_attention.py
moduleZoo/attention/conv_self_attention.py
moduleZoo/attention/linear_multi_head_attention.py
moduleZoo/attention/utils.py
moduleZoo/convolution/__init__.py
moduleZoo/convolution/convblocks.py
moduleZoo/convolution/invertedconvblocks.py
moduleZoo/dense/__init__.py
moduleZoo/dense/denseblocks.py
moduleZoo/graphs/__init__.py
moduleZoo/graphs/grah_conv.py
moduleZoo/graphs/utils.py
moduleZoo/resblocks/__init__.py
moduleZoo/resblocks/bottleneckresidual.py
moduleZoo/resblocks/invertedresidual.py
moduleZoo/resblocks/residual.py
mzExtras/LARC.py
mzExtras/__init__.py
mzLosses/contrastive.py
ModuleZooTorch-1.1.3a0.dist-info/LICENSE
ModuleZooTorch-1.1.3a0.dist-info/METADATA
ModuleZooTorch-1.1.3a0.dist-info/WHEEL
ModuleZooTorch-1.1.3a0.dist-info/top_level.txt
ModuleZooTorch-1.1.3a0.dist-info/RECORD
